{"id":"http://dbpedia.org/resource/Javier_Pastore", "docUri":"/players/Javier_Pastore.json", "abstract":"Javier Matías Pastore (born 20 June 1989) is an Argentine footballer who currently plays for Ligue 1 club Paris Saint-Germain and the Argentina national football team as an attacking midfielder.He started his career with Talleres and then Huracán in his native Argentina before moving to Serie A team Palermo in 2009 for a fee of reported €4.7 million. In 2011 Ligue 1 side Paris Saint-Germain bought him for a reported €39.8 million.", "comment":"Javier Matías Pastore (born 20 June 1989) is an Argentine footballer who currently plays for Ligue 1 club Paris Saint-Germain and the Argentina national football team as an attacking midfielder.He started his career with Talleres and then Huracán in his native Argentina before moving to Serie A team Palermo in 2009 for a fee of reported €4.7 million. In 2011 Ligue 1 side Paris Saint-Germain bought him for a reported €39.8 million.", "birthYear":"1989+02:00", "height":"1.87", "number":"27", "position":"http://dbpedia.org/resource/Midfielder", "thumbnail":"http://commons.wikimedia.org/wiki/Special:FilePath/Javier_Pastore_(cropped).jpg?width=300", "birthDate":"1989-06-20+02:00", "currentclub":"http://dbpedia.org/resource/Paris_Saint-Germain_F.C.", "nationalteam":"http://dbpedia.org/resource/Argentina_national_football_team", "nationalyears":"2010", "shortDescription":"Argentine footballer", "depiction":"http://commons.wikimedia.org/wiki/Special:FilePath/Javier_Pastore_(cropped).jpg", "givenName":"Javier", "isPrimaryTopicOf":"http://en.wikipedia.org/wiki/Javier_Pastore", "name":["Javier Matías Pastore", "Javier Pastore", "Pastore, Javier"], "surname":"Pastore"}