{"id":"http://dbpedia.org/resource/Kagisho_Dikgacoi", "docUri":"/players/Kagisho_Dikgacoi.json", "abstract":"Kagisho Evidence Dikgacoi /diːˈxʌʃwɑː/ (born 24 November 1984) is a South African footballer who plays for Crystal Palace and South Africa.He made his international debut in 2007, and since then has earned 54 caps, scoring twice. He played at the Africa Cup of Nations in 2008 and 2013, and at the 2010 FIFA World Cup.", "comment":"Kagisho Evidence Dikgacoi /diːˈxʌʃwɑː/ (born 24 November 1984) is a South African footballer who plays for Crystal Palace and South Africa.He made his international debut in 2007, and since then has earned 54 caps, scoring twice. He played at the Africa Cup of Nations in 2008 and 2013, and at the 2010 FIFA World Cup.", "birthYear":"1984+02:00", "height":"0", "number":"8", "position":"http://dbpedia.org/resource/Midfielder", "thumbnail":"http://commons.wikimedia.org/wiki/Special:FilePath/Kagisho_Dikgacoi.jpg?width=300", "birthDate":"1984-11-24+02:00", "currentclub":"http://dbpedia.org/resource/Crystal_Palace_F.C.", "nationalteam":"http://dbpedia.org/resource/South_Africa_national_football_team", "nationalyears":"2007", "shortDescription":"South African footballer", "depiction":"http://commons.wikimedia.org/wiki/Special:FilePath/Kagisho_Dikgacoi.jpg", "givenName":"Kagisho", "isPrimaryTopicOf":"http://en.wikipedia.org/wiki/Kagisho_Dikgacoi", "name":["Dikgacoi, Kagisho", "Kagisho Dikgacoi", "Kagisho Evidence Dikgacoi"], "surname":"Dikgacoi"}