{"id":"http://dbpedia.org/resource/Marcus_Tulio_Tanaka", "docUri":"/players/Marcus_Tulio_Tanaka.json", "abstract":"Marcus Tulio Lyuji Murzani Tanaka (田中 マルクス 闘莉王, Tanaka Marukusu Tūrio, born Marcus Túlio Lyuji Murzani Tanaka on 24 April 1981 in Palmeira d'Oeste, São Paulo, Brazil), commonly known as Tulio, is a Brazilian-born Japanese footballer who plays for the J. League Division 1 club Nagoya Grampus.", "comment":"Marcus Tulio Lyuji Murzani Tanaka (田中 マルクス 闘莉王, Tanaka Marukusu Tūrio, born Marcus Túlio Lyuji Murzani Tanaka on 24 April 1981 in Palmeira d'Oeste, São Paulo, Brazil), commonly known as Tulio, is a Brazilian-born Japanese footballer who plays for the J. League Division 1 club Nagoya Grampus.", "birthYear":"1981+02:00", "height":"1.8542", "number":"4", "position":"http://dbpedia.org/resource/Defender_(association_football)", "thumbnail":"http://commons.wikimedia.org/wiki/Special:FilePath/Tulio_20080622.jpg?width=300", "birthDate":"1981-04-24+02:00", "currentclub":"http://dbpedia.org/resource/Nagoya_Grampus", "nationalteam":["http://dbpedia.org/resource/Japan_national_football_team", "http://dbpedia.org/resource/Japan_national_under-23_football_team"], "nationalyears":["2004", 2006], "shortDescription":"Footballer", "depiction":"http://commons.wikimedia.org/wiki/Special:FilePath/Tulio_20080622.jpg", "givenName":"Marcus Tulio", "isPrimaryTopicOf":"http://en.wikipedia.org/wiki/Marcus_Tulio_Tanaka", "name":["Marcus Tulio Lyuji Murzani Tanaka", "Marcus Tulio Tanaka", "Tanaka, Marcus Tulio"], "surname":"Tanaka"}