{"id":"http://dbpedia.org/resource/Reto_Ziegler", "docUri":"/players/Reto_Ziegler.json", "abstract":"Reto Pirmin Ziegler (born 16 January 1986) is a Swiss footballer who plays for Serie A club Sassuolo on loan from Juventus.He has played top-flight football in six different countries, and earned 32 international caps for Switzerland, playing at the 2010 FIFA World Cup.", "comment":"Reto Pirmin Ziegler (born 16 January 1986) is a Swiss footballer who plays for Serie A club Sassuolo on loan from Juventus.He has played top-flight football in six different countries, and earned 32 international caps for Switzerland, playing at the 2010 FIFA World Cup.", "birthYear":"1986+02:00", "height":"1.8299999999999998", "number":"86", "position":"http://dbpedia.org/resource/Defender_(association_football)", "thumbnail":"http://commons.wikimedia.org/wiki/Special:FilePath/Reto_Ziegler_2012.jpg?width=300", "birthDate":"1986-01-16+02:00", "currentclub":"http://dbpedia.org/resource/U.S._Sassuolo_Calcio", "nationalteam":["http://dbpedia.org/resource/Switzerland_national_football_team", "http://dbpedia.org/resource/Switzerland_national_under-17_football_team", "http://dbpedia.org/resource/Switzerland_national_under-21_football_team"], "nationalyears":["2004", 2005], "shortDescription":"footballer", "depiction":"http://commons.wikimedia.org/wiki/Special:FilePath/Reto_Ziegler_2012.jpg", "givenName":"Reto", "homepage":"http://www.sampdoria.it/index.php?option=com_teammanager&Itemid=109&task=player&playerid=52", "isPrimaryTopicOf":"http://en.wikipedia.org/wiki/Reto_Ziegler", "name":["Reto Pirmin Ziegler", "Reto Ziegler", "Ziegler, Reto"], "surname":"Ziegler"}