<?xml version="1.0" encoding="UTF-8"?><sem:triples xmlns:sem="http://marklogic.com/semantics"><sem:origin>file:///home/cgreer/source/semantics-tutorial/data/rdf/players/Samuel_Inkoom.n3</sem:origin><sem:triple><sem:subject>http://dbpedia.org/resource/Samuel_Inkoom</sem:subject><sem:predicate>http://dbpedia.org/ontology/birthDate</sem:predicate><sem:object datatype="http://www.w3.org/2001/XMLSchema#date">1989-06-01+02:00</sem:object></sem:triple><sem:triple><sem:subject>http://dbpedia.org/resource/Samuel_Inkoom</sem:subject><sem:predicate>http://www.w3.org/1999/02/22-rdf-syntax-ns#type</sem:predicate><sem:object>http://www.w3.org/2002/07/owl#Thing</sem:object></sem:triple><sem:triple><sem:subject>http://dbpedia.org/resource/Samuel_Inkoom</sem:subject><sem:predicate>http://dbpedia.org/property/goals</sem:predicate><sem:object datatype="http://www.w3.org/2001/XMLSchema#integer">0</sem:object></sem:triple><sem:triple><sem:subject>http://dbpedia.org/resource/Samuel_Inkoom</sem:subject><sem:predicate>http://www.w3.org/2000/01/rdf-schema#comment</sem:predicate><sem:object xml:lang="fr">Samuel Eboue Inkoom, né le 22 août 1989 à Sekondi Hasaacas, est un footballeur international ghanéen qui évolue au poste de latéral droit.</sem:object></sem:triple><sem:triple><sem:subject>http://dbpedia.org/resource/Samuel_Inkoom</sem:subject><sem:predicate>http://www.w3.org/1999/02/22-rdf-syntax-ns#type</sem:predicate><sem:object>http://dbpedia.org/ontology/Agent</sem:object></sem:triple><sem:triple><sem:subject>http://dbpedia.org/resource/Samuel_Inkoom</sem:subject><sem:predicate>http://www.w3.org/1999/02/22-rdf-syntax-ns#type</sem:predicate><sem:object>http://dbpedia.org/class/yago/Object100002684</sem:object></sem:triple><sem:triple><sem:subject>http://dbpedia.org/resource/Samuel_Inkoom</sem:subject><sem:predicate>http://purl.org/dc/terms/subject</sem:predicate><sem:object>http://dbpedia.org/resource/Category:Asante_Kotoko_F.C._players</sem:object></sem:triple><sem:triple><sem:subject>http://dbpedia.org/resource/Samuel_Inkoom</sem:subject><sem:predicate>http://www.w3.org/1999/02/22-rdf-syntax-ns#type</sem:predicate><sem:object>http://dbpedia.org/class/yago/LivingPeople</sem:object></sem:triple><sem:triple><sem:subject>http://dbpedia.org/resource/Samuel_Inkoom</sem:subject><sem:predicate>http://dbpedia.org/ontology/careerStation</sem:predicate><sem:object>http://dbpedia.org/resource/Samuel_Inkoom__3</sem:object></sem:triple><sem:triple><sem:subject>http://dbpedia.org/resource/Samuel_Inkoom</sem:subject><sem:predicate>http://dbpedia.org/property/nationalteam</sem:predicate><sem:object>http://dbpedia.org/resource/Ghana_national_under-20_football_team</sem:object></sem:triple><sem:triple><sem:subject>http://dbpedia.org/resource/Samuel_Inkoom</sem:subject><sem:predicate>http://www.w3.org/2002/07/owl#sameAs</sem:predicate><sem:object>http://wikidata.org/entity/Q350168</sem:object></sem:triple><sem:triple><sem:subject>http://dbpedia.org/resource/Samuel_Inkoom</sem:subject><sem:predicate>http://purl.org/dc/terms/subject</sem:predicate><sem:object>http://dbpedia.org/resource/Category:Ghanaian_footballers</sem:object></sem:triple><sem:triple><sem:subject>http://dbpedia.org/resource/Samuel_Inkoom</sem:subject><sem:predicate>http://www.w3.org/2002/07/owl#sameAs</sem:predicate><sem:object>http://ru.dbpedia.org/resource/Инкум,_Самуэль</sem:object></sem:triple><sem:triple><sem:subject>http://dbpedia.org/resource/Samuel_Inkoom</sem:subject><sem:predicate>http://purl.org/dc/terms/subject</sem:predicate><sem:object>http://dbpedia.org/resource/Category:Ligue_1_players</sem:object></sem:triple><sem:triple><sem:subject>http://dbpedia.org/resource/Samuel_Inkoom</sem:subject><sem:predicate>http://dbpedia.org/ontology/careerStation</sem:predicate><sem:object>http://dbpedia.org/resource/Samuel_Inkoom__7</sem:object></sem:triple><sem:triple><sem:subject>http://dbpedia.org/resource/Samuel_Inkoom</sem:subject><sem:predicate>http://www.w3.org/2002/07/owl#sameAs</sem:predicate><sem:object>http://sv.dbpedia.org/resource/Samuel_Inkoom</sem:object></sem:triple><sem:triple><sem:subject>http://dbpedia.org/resource/Samuel_Inkoom</sem:subject><sem:predicate>http://dbpedia.org/ontology/birthPlace</sem:predicate><sem:object>http://dbpedia.org/resource/Sekondi-Takoradi</sem:object></sem:triple><sem:triple><sem:subject>http://dbpedia.org/resource/Samuel_Inkoom</sem:subject><sem:predicate>http://dbpedia.org/property/clubs</sem:predicate><sem:object>http://dbpedia.org/resource/Asante_Kotoko_SC</sem:object></sem:triple><sem:triple><sem:subject>http://dbpedia.org/resource/Samuel_Inkoom</sem:subject><sem:predicate>http://dbpedia.org/property/placeOfBirth</sem:predicate><sem:object datatype="http://www.w3.org/2001/XMLSchema#string">Sekondi-Takoradi, Ghana</sem:object></sem:triple><sem:triple><sem:subject>http://dbpedia.org/resource/Samuel_Inkoom</sem:subject><sem:predicate>http://dbpedia.org/property/name</sem:predicate><sem:object datatype="http://www.w3.org/2001/XMLSchema#string">Inkoom, Samuel</sem:object></sem:triple><sem:triple><sem:subject>http://dbpedia.org/resource/Samuel_Inkoom</sem:subject><sem:predicate>http://www.w3.org/2002/07/owl#sameAs</sem:predicate><sem:object>http://wikidata.dbpedia.org/resource/Q350168</sem:object></sem:triple><sem:triple><sem:subject>http://dbpedia.org/resource/Samuel_Inkoom</sem:subject><sem:predicate>http://xmlns.com/foaf/0.1/depiction</sem:predicate><sem:object>http://commons.wikimedia.org/wiki/Special:FilePath/Samuel_Inkoom.jpg</sem:object></sem:triple><sem:triple><sem:subject>http://dbpedia.org/resource/Samuel_Inkoom</sem:subject><sem:predicate>http://www.w3.org/1999/02/22-rdf-syntax-ns#type</sem:predicate><sem:object>http://dbpedia.org/class/yago/SCAdelaidePlayers</sem:object></sem:triple><sem:triple><sem:subject>http://fi.dbpedia.org/resource/Samuel_Inkoom</sem:subject><sem:predicate>http://www.w3.org/2002/07/owl#sameAs</sem:predicate><sem:object>http://dbpedia.org/resource/Samuel_Inkoom</sem:object></sem:triple><sem:triple><sem:subject>http://nn.dbpedia.org/resource/Samuel_Inkoom</sem:subject><sem:predicate>http://www.w3.org/2002/07/owl#sameAs</sem:predicate><sem:object>http://dbpedia.org/resource/Samuel_Inkoom</sem:object></sem:triple><sem:triple><sem:subject>http://dbpedia.org/resource/2010_FIFA_World_Cup_squads</sem:subject><sem:predicate>http://dbpedia.org/property/name</sem:predicate><sem:object>http://dbpedia.org/resource/Samuel_Inkoom</sem:object></sem:triple><sem:triple><sem:subject>http://en.wikipedia.org/wiki/Samuel_Inkoom</sem:subject><sem:predicate>http://xmlns.com/foaf/0.1/primaryTopic</sem:predicate><sem:object>http://dbpedia.org/resource/Samuel_Inkoom</sem:object></sem:triple><sem:triple><sem:subject>http://uk.dbpedia.org/resource/Самуель_Інкум</sem:subject><sem:predicate>http://www.w3.org/2002/07/owl#sameAs</sem:predicate><sem:object>http://dbpedia.org/resource/Samuel_Inkoom</sem:object></sem:triple><sem:triple><sem:subject>http://wikidata.dbpedia.org/resource/Q350168</sem:subject><sem:predicate>http://www.w3.org/2002/07/owl#sameAs</sem:predicate><sem:object>http://dbpedia.org/resource/Samuel_Inkoom</sem:object></sem:triple><sem:triple><sem:subject>http://dbpedia.org/resource/2012_Africa_Cup_of_Nations_squads</sem:subject><sem:predicate>http://dbpedia.org/property/name</sem:predicate><sem:object>http://dbpedia.org/resource/Samuel_Inkoom</sem:object></sem:triple><sem:triple><sem:subject>http://dbpedia.org/resource/2012%E2%80%9313_FC_Dnipro_Dnipropetrovsk_season__Samuel_Inkoom__2</sem:subject><sem:predicate>http://dbpedia.org/ontology/currentMember</sem:predicate><sem:object>http://dbpedia.org/resource/Samuel_Inkoom</sem:object></sem:triple><sem:triple><sem:subject>http://dbpedia.org/resource/Ghana_national_under-20_football_team</sem:subject><sem:predicate>http://dbpedia.org/property/name</sem:predicate><sem:object>http://dbpedia.org/resource/Samuel_Inkoom</sem:object></sem:triple><sem:triple><sem:subject>http://ja.dbpedia.org/resource/サミュエル・インコーム</sem:subject><sem:predicate>http://www.w3.org/2002/07/owl#sameAs</sem:predicate><sem:object>http://dbpedia.org/resource/Samuel_Inkoom</sem:object></sem:triple><sem:triple><sem:subject>http://dbpedia.org/resource/2012%E2%80%9313_FC_Dnipro_Dnipropetrovsk_season</sem:subject><sem:predicate>http://dbpedia.org/property/name</sem:predicate><sem:object>http://dbpedia.org/resource/Samuel_Inkoom</sem:object></sem:triple><sem:triple><sem:subject>http://dbpedia.org/resource/2009%E2%80%9310_FC_Basel_season</sem:subject><sem:predicate>http://dbpedia.org/property/name</sem:predicate><sem:object>http://dbpedia.org/resource/Samuel_Inkoom</sem:object></sem:triple><sem:triple><sem:subject>http://pt.dbpedia.org/resource/Samuel_Inkoom</sem:subject><sem:predicate>http://www.w3.org/2002/07/owl#sameAs</sem:predicate><sem:object>http://dbpedia.org/resource/Samuel_Inkoom</sem:object></sem:triple><sem:triple><sem:subject>http://de.dbpedia.org/resource/Samuel_Inkoom</sem:subject><sem:predicate>http://www.w3.org/2002/07/owl#sameAs</sem:predicate><sem:object>http://dbpedia.org/resource/Samuel_Inkoom</sem:object></sem:triple><sem:triple><sem:subject>http://dbpedia.org/resource/S.C._Adelaide</sem:subject><sem:predicate>http://dbpedia.org/property/name</sem:predicate><sem:object>http://dbpedia.org/resource/Samuel_Inkoom</sem:object></sem:triple><sem:triple><sem:subject>http://dbpedia.org/resource/2012%E2%80%9313_FC_Dnipro_Dnipropetrovsk_season__Samuel_Inkoom__1</sem:subject><sem:predicate>http://dbpedia.org/ontology/currentMember</sem:predicate><sem:object>http://dbpedia.org/resource/Samuel_Inkoom</sem:object></sem:triple><sem:triple><sem:subject>http://fr.dbpedia.org/resource/Samuel_Inkoom</sem:subject><sem:predicate>http://www.w3.org/2002/07/owl#sameAs</sem:predicate><sem:object>http://dbpedia.org/resource/Samuel_Inkoom</sem:object></sem:triple><sem:triple><sem:subject>http://mr.dbpedia.org/resource/सॅम्युएल_इंकूम</sem:subject><sem:predicate>http://www.w3.org/2002/07/owl#sameAs</sem:predicate><sem:object>http://dbpedia.org/resource/Samuel_Inkoom</sem:object></sem:triple><sem:triple><sem:subject>http://dbpedia.org/resource/S.C._Adelaide__Samuel_Inkoom__1</sem:subject><sem:predicate>http://dbpedia.org/ontology/currentMember</sem:predicate><sem:object>http://dbpedia.org/resource/Samuel_Inkoom</sem:object></sem:triple><sem:triple><sem:subject>http://ru.dbpedia.org/resource/Инкум,_Самуэль</sem:subject><sem:predicate>http://www.w3.org/2002/07/owl#sameAs</sem:predicate><sem:object>http://dbpedia.org/resource/Samuel_Inkoom</sem:object></sem:triple><sem:triple><sem:subject>http://nl.dbpedia.org/resource/Samuel_Inkoom</sem:subject><sem:predicate>http://www.w3.org/2002/07/owl#sameAs</sem:predicate><sem:object>http://dbpedia.org/resource/Samuel_Inkoom</sem:object></sem:triple><sem:triple><sem:subject>http://dbpedia.org/resource/2009%E2%80%9310_FC_Basel_season__Samuel_Inkoom__2</sem:subject><sem:predicate>http://dbpedia.org/ontology/currentMember</sem:predicate><sem:object>http://dbpedia.org/resource/Samuel_Inkoom</sem:object></sem:triple><sem:triple><sem:subject>http://dbpedia.org/resource/FC_Dnipro_Dnipropetrovsk__Samuel_Inkoom__1</sem:subject><sem:predicate>http://dbpedia.org/ontology/currentMember</sem:predicate><sem:object>http://dbpedia.org/resource/Samuel_Inkoom</sem:object></sem:triple></sem:triples>