<?xml version="1.0" encoding="UTF-8"?><sem:triples xmlns:sem="http://marklogic.com/semantics"><sem:origin>file:///home/cgreer/source/semantics-tutorial/data/rdf/players/Reto_Ziegler.n3</sem:origin><sem:triple><sem:subject>http://dbpedia.org/resource/List_of_Russian_football_transfers_summer_2012</sem:subject><sem:predicate>http://dbpedia.org/ontology/currentMember</sem:predicate><sem:object>http://dbpedia.org/resource/Reto_Ziegler</sem:object></sem:triple><sem:triple><sem:subject>http://dbpedia.org/resource/List_of_Russian_football_transfers_summer_2012</sem:subject><sem:predicate>http://dbpedia.org/property/name</sem:predicate><sem:object>http://dbpedia.org/resource/Reto_Ziegler</sem:object></sem:triple><sem:triple><sem:subject>http://dbpedia.org/resource/2012%E2%80%9313_FC_Lokomotiv_Moscow_season__Reto_Ziegler__1</sem:subject><sem:predicate>http://dbpedia.org/ontology/currentMember</sem:predicate><sem:object>http://dbpedia.org/resource/Reto_Ziegler</sem:object></sem:triple><sem:triple><sem:subject>http://dbpedia.org/resource/2009%E2%80%9310_U.C._Sampdoria_season__Reto_Ziegler__1</sem:subject><sem:predicate>http://dbpedia.org/ontology/currentMember</sem:predicate><sem:object>http://dbpedia.org/resource/Reto_Ziegler</sem:object></sem:triple><sem:triple><sem:subject>http://it.dbpedia.org/resource/Reto_Ziegler</sem:subject><sem:predicate>http://www.w3.org/2002/07/owl#sameAs</sem:predicate><sem:object>http://dbpedia.org/resource/Reto_Ziegler</sem:object></sem:triple><sem:triple><sem:subject>http://dbpedia.org/resource/2006%E2%80%9307_Tottenham_Hotspur_F.C._season__Reto_Ziegler__1</sem:subject><sem:predicate>http://dbpedia.org/ontology/currentMember</sem:predicate><sem:object>http://dbpedia.org/resource/Reto_Ziegler</sem:object></sem:triple><sem:triple><sem:subject>http://no.dbpedia.org/resource/Reto_Ziegler</sem:subject><sem:predicate>http://www.w3.org/2002/07/owl#sameAs</sem:predicate><sem:object>http://dbpedia.org/resource/Reto_Ziegler</sem:object></sem:triple><sem:triple><sem:subject>http://dbpedia.org/resource/2008%E2%80%9309_U.C._Sampdoria_season</sem:subject><sem:predicate>http://dbpedia.org/property/name</sem:predicate><sem:object>http://dbpedia.org/resource/Reto_Ziegler</sem:object></sem:triple><sem:triple><sem:subject>http://dbpedia.org/resource/2009%E2%80%9310_U.C._Sampdoria_season</sem:subject><sem:predicate>http://dbpedia.org/property/name</sem:predicate><sem:object>http://dbpedia.org/resource/Reto_Ziegler</sem:object></sem:triple><sem:triple><sem:subject>http://hu.dbpedia.org/resource/Reto_Ziegler</sem:subject><sem:predicate>http://www.w3.org/2002/07/owl#sameAs</sem:predicate><sem:object>http://dbpedia.org/resource/Reto_Ziegler</sem:object></sem:triple><sem:triple><sem:subject>http://en.wikipedia.org/wiki/Reto_Ziegler</sem:subject><sem:predicate>http://xmlns.com/foaf/0.1/primaryTopic</sem:predicate><sem:object>http://dbpedia.org/resource/Reto_Ziegler</sem:object></sem:triple><sem:triple><sem:subject>http://dbpedia.org/resource/List_of_Russian_football_transfers_winter_2012%E2%80%9313</sem:subject><sem:predicate>http://dbpedia.org/ontology/currentMember</sem:predicate><sem:object>http://dbpedia.org/resource/Reto_Ziegler</sem:object></sem:triple><sem:triple><sem:subject>http://dbpedia.org/resource/List_of_Russian_football_transfers_winter_2012%E2%80%9313</sem:subject><sem:predicate>http://dbpedia.org/property/name</sem:predicate><sem:object>http://dbpedia.org/resource/Reto_Ziegler</sem:object></sem:triple><sem:triple><sem:subject>http://he.dbpedia.org/resource/רטו_ציגלר</sem:subject><sem:predicate>http://www.w3.org/2002/07/owl#sameAs</sem:predicate><sem:object>http://dbpedia.org/resource/Reto_Ziegler</sem:object></sem:triple><sem:triple><sem:subject>http://pl.dbpedia.org/resource/Reto_Ziegler</sem:subject><sem:predicate>http://www.w3.org/2002/07/owl#sameAs</sem:predicate><sem:object>http://dbpedia.org/resource/Reto_Ziegler</sem:object></sem:triple><sem:triple><sem:subject>http://zh.dbpedia.org/resource/列圖·薛基拿</sem:subject><sem:predicate>http://www.w3.org/2002/07/owl#sameAs</sem:predicate><sem:object>http://dbpedia.org/resource/Reto_Ziegler</sem:object></sem:triple><sem:triple><sem:subject>http://dbpedia.org/resource/2012%E2%80%9313_FC_Lokomotiv_Moscow_season</sem:subject><sem:predicate>http://dbpedia.org/property/name</sem:predicate><sem:object>http://dbpedia.org/resource/Reto_Ziegler</sem:object></sem:triple><sem:triple><sem:subject>http://dbpedia.org/resource/List_of_Turkish_football_transfers_summer_2013</sem:subject><sem:predicate>http://dbpedia.org/ontology/currentMember</sem:predicate><sem:object>http://dbpedia.org/resource/Reto_Ziegler</sem:object></sem:triple><sem:triple><sem:subject>http://dbpedia.org/resource/List_of_Turkish_football_transfers_summer_2013</sem:subject><sem:predicate>http://dbpedia.org/property/name</sem:predicate><sem:object>http://dbpedia.org/resource/Reto_Ziegler</sem:object></sem:triple><sem:triple><sem:subject>http://ar.dbpedia.org/resource/ريتو_زيغلر</sem:subject><sem:predicate>http://www.w3.org/2002/07/owl#sameAs</sem:predicate><sem:object>http://dbpedia.org/resource/Reto_Ziegler</sem:object></sem:triple><sem:triple><sem:subject>http://dbpedia.org/resource/2005%E2%80%9306_Tottenham_Hotspur_F.C._season</sem:subject><sem:predicate>http://dbpedia.org/property/name</sem:predicate><sem:object>http://dbpedia.org/resource/Reto_Ziegler</sem:object></sem:triple><sem:triple><sem:subject>http://de.dbpedia.org/resource/Reto_Ziegler</sem:subject><sem:predicate>http://www.w3.org/2002/07/owl#sameAs</sem:predicate><sem:object>http://dbpedia.org/resource/Reto_Ziegler</sem:object></sem:triple><sem:triple><sem:subject>http://mr.dbpedia.org/resource/रेटो_झीग्लर</sem:subject><sem:predicate>http://www.w3.org/2002/07/owl#sameAs</sem:predicate><sem:object>http://dbpedia.org/resource/Reto_Ziegler</sem:object></sem:triple><sem:triple><sem:subject>http://dbpedia.org/resource/2012%E2%80%9313_Juventus_F.C._season__Reto_Ziegler__1</sem:subject><sem:predicate>http://dbpedia.org/ontology/currentMember</sem:predicate><sem:object>http://dbpedia.org/resource/Reto_Ziegler</sem:object></sem:triple><sem:triple><sem:subject>http://dbpedia.org/resource/2011%E2%80%9312_Fenerbah%C3%A7e_S.K._season</sem:subject><sem:predicate>http://dbpedia.org/property/p</sem:predicate><sem:object>http://dbpedia.org/resource/Reto_Ziegler</sem:object></sem:triple><sem:triple><sem:subject>http://dbpedia.org/resource/2011%E2%80%9312_Fenerbah%C3%A7e_S.K._season</sem:subject><sem:predicate>http://dbpedia.org/property/name</sem:predicate><sem:object>http://dbpedia.org/resource/Reto_Ziegler</sem:object></sem:triple><sem:triple><sem:subject>http://dbpedia.org/resource/2004%E2%80%9305_Tottenham_Hotspur_F.C._season</sem:subject><sem:predicate>http://dbpedia.org/property/name</sem:predicate><sem:object>http://dbpedia.org/resource/Reto_Ziegler</sem:object></sem:triple><sem:triple><sem:subject>http://dbpedia.org/resource/Juventus_F.C.__Reto_Ziegler__1</sem:subject><sem:predicate>http://dbpedia.org/ontology/currentMember</sem:predicate><sem:object>http://dbpedia.org/resource/Reto_Ziegler</sem:object></sem:triple><sem:triple><sem:subject>http://dbpedia.org/resource/Ziegler</sem:subject><sem:predicate>http://dbpedia.org/ontology/wikiPageDisambiguates</sem:predicate><sem:object>http://dbpedia.org/resource/Reto_Ziegler</sem:object></sem:triple><sem:triple><sem:subject>http://bg.dbpedia.org/resource/Рето_Циглер</sem:subject><sem:predicate>http://www.w3.org/2002/07/owl#sameAs</sem:predicate><sem:object>http://dbpedia.org/resource/Reto_Ziegler</sem:object></sem:triple><sem:triple><sem:subject>http://dbpedia.org/resource/2011%E2%80%9312_Fenerbah%C3%A7e_S.K._season__Reto_Ziegler__1</sem:subject><sem:predicate>http://dbpedia.org/ontology/currentMember</sem:predicate><sem:object>http://dbpedia.org/resource/Reto_Ziegler</sem:object></sem:triple><sem:triple><sem:subject>http://simple.dbpedia.org/resource/Reto_Ziegler</sem:subject><sem:predicate>http://www.w3.org/2002/07/owl#sameAs</sem:predicate><sem:object>http://dbpedia.org/resource/Reto_Ziegler</sem:object></sem:triple><sem:triple><sem:subject>http://fi.dbpedia.org/resource/Reto_Ziegler</sem:subject><sem:predicate>http://www.w3.org/2002/07/owl#sameAs</sem:predicate><sem:object>http://dbpedia.org/resource/Reto_Ziegler</sem:object></sem:triple><sem:triple><sem:subject>http://tr.dbpedia.org/resource/Reto_Ziegler</sem:subject><sem:predicate>http://www.w3.org/2002/07/owl#sameAs</sem:predicate><sem:object>http://dbpedia.org/resource/Reto_Ziegler</sem:object></sem:triple><sem:triple><sem:subject>http://dbpedia.org/resource/2012%E2%80%9313_Fenerbah%C3%A7e_S.K._season</sem:subject><sem:predicate>http://dbpedia.org/property/p</sem:predicate><sem:object>http://dbpedia.org/resource/Reto_Ziegler</sem:object></sem:triple><sem:triple><sem:subject>http://nl.dbpedia.org/resource/Reto_Ziegler</sem:subject><sem:predicate>http://www.w3.org/2002/07/owl#sameAs</sem:predicate><sem:object>http://dbpedia.org/resource/Reto_Ziegler</sem:object></sem:triple><sem:triple><sem:subject>http://sl.dbpedia.org/resource/Reto_Ziegler</sem:subject><sem:predicate>http://www.w3.org/2002/07/owl#sameAs</sem:predicate><sem:object>http://dbpedia.org/resource/Reto_Ziegler</sem:object></sem:triple><sem:triple><sem:subject>http://id.dbpedia.org/resource/Reto_Ziegler</sem:subject><sem:predicate>http://www.w3.org/2002/07/owl#sameAs</sem:predicate><sem:object>http://dbpedia.org/resource/Reto_Ziegler</sem:object></sem:triple><sem:triple><sem:subject>http://dbpedia.org/resource/Switzerland_national_football_team</sem:subject><sem:predicate>http://dbpedia.org/property/name</sem:predicate><sem:object>http://dbpedia.org/resource/Reto_Ziegler</sem:object></sem:triple><sem:triple><sem:subject>http://dbpedia.org/resource/2010_FIFA_World_Cup_squads</sem:subject><sem:predicate>http://dbpedia.org/property/name</sem:predicate><sem:object>http://dbpedia.org/resource/Reto_Ziegler</sem:object></sem:triple><sem:triple><sem:subject>http://dbpedia.org/resource/Reto_Ziegler</sem:subject><sem:predicate>http://dbpedia.org/property/years</sem:predicate><sem:object datatype="http://www.w3.org/2001/XMLSchema#integer">2007</sem:object></sem:triple><sem:triple><sem:subject>http://dbpedia.org/resource/Reto_Ziegler</sem:subject><sem:predicate>http://dbpedia.org/ontology/number</sem:predicate><sem:object datatype="http://www.w3.org/2001/XMLSchema#integer">86</sem:object></sem:triple><sem:triple><sem:subject>http://dbpedia.org/resource/Reto_Ziegler</sem:subject><sem:predicate>http://purl.org/dc/terms/subject</sem:predicate><sem:object>http://dbpedia.org/resource/Category:Wigan_Athletic_F.C._players</sem:object></sem:triple><sem:triple><sem:subject>http://dbpedia.org/resource/Reto_Ziegler</sem:subject><sem:predicate>http://www.w3.org/2000/01/rdf-schema#comment</sem:predicate><sem:object xml:lang="es">Reto Ziegler (Ginebra, Suiza, 16 de enero de 1986) es un futbolista suizo. Juega de lateral izquierdo y su equipo actual es el U. S. Sassuolo de la Serie A de Italia.</sem:object></sem:triple><sem:triple><sem:subject>http://dbpedia.org/resource/Reto_Ziegler</sem:subject><sem:predicate>http://www.w3.org/2002/07/owl#sameAs</sem:predicate><sem:object>http://hu.dbpedia.org/resource/Reto_Ziegler</sem:object></sem:triple><sem:triple><sem:subject>http://dbpedia.org/resource/Reto_Ziegler</sem:subject><sem:predicate>http://dbpedia.org/ontology/wikiPageExternalLink</sem:predicate><sem:object>http://www.gazzetta.it/Calciomercato/31-08-2011/juve-no-stop-802681156771.shtml</sem:object></sem:triple><sem:triple><sem:subject>http://dbpedia.org/resource/Reto_Ziegler</sem:subject><sem:predicate>http://dbpedia.org/property/currentclub</sem:predicate><sem:object>http://dbpedia.org/resource/U.S._Sassuolo_Calcio</sem:object></sem:triple><sem:triple><sem:subject>http://dbpedia.org/resource/Reto_Ziegler</sem:subject><sem:predicate>http://www.w3.org/2002/07/owl#sameAs</sem:predicate><sem:object>http://sl.dbpedia.org/resource/Reto_Ziegler</sem:object></sem:triple><sem:triple><sem:subject>http://dbpedia.org/resource/Reto_Ziegler</sem:subject><sem:predicate>http://purl.org/dc/terms/subject</sem:predicate><sem:object>http://dbpedia.org/resource/Category:U.C._Sampdoria_players</sem:object></sem:triple><sem:triple><sem:subject>http://dbpedia.org/resource/Reto_Ziegler</sem:subject><sem:predicate>http://dbpedia.org/ontology/careerStation</sem:predicate><sem:object>http://dbpedia.org/resource/Reto_Ziegler__14</sem:object></sem:triple><sem:triple><sem:subject>http://dbpedia.org/resource/Reto_Ziegler</sem:subject><sem:predicate>http://dbpedia.org/property/years</sem:predicate><sem:object datatype="http://www.w3.org/2001/XMLSchema#integer">2011</sem:object></sem:triple><sem:triple><sem:subject>http://dbpedia.org/resource/Reto_Ziegler</sem:subject><sem:predicate>http://www.w3.org/2002/07/owl#sameAs</sem:predicate><sem:object>http://rdf.freebase.com/ns/m.086wv6</sem:object></sem:triple><sem:triple><sem:subject>http://dbpedia.org/resource/Reto_Ziegler</sem:subject><sem:predicate>http://xmlns.com/foaf/0.1/name</sem:predicate><sem:object datatype="http://www.w3.org/2001/XMLSchema#string">Ziegler, Reto</sem:object></sem:triple><sem:triple><sem:subject>http://dbpedia.org/resource/Reto_Ziegler</sem:subject><sem:predicate>http://www.w3.org/2002/07/owl#sameAs</sem:predicate><sem:object>http://sw.cyc.com/concept/Mx4rnEgp9iqHSKuT9qGIAPKFyw</sem:object></sem:triple><sem:triple><sem:subject>http://dbpedia.org/resource/Reto_Ziegler</sem:subject><sem:predicate>http://dbpedia.org/property/clubs</sem:predicate><sem:object>http://dbpedia.org/resource/Grasshopper_Club_Z%C3%BCrich</sem:object></sem:triple><sem:triple><sem:subject>http://dbpedia.org/resource/Reto_Ziegler</sem:subject><sem:predicate>http://dbpedia.org/property/nationalteam</sem:predicate><sem:object>http://dbpedia.org/resource/Switzerland_national_football_team</sem:object></sem:triple><sem:triple><sem:subject>http://dbpedia.org/resource/Reto_Ziegler</sem:subject><sem:predicate>http://dbpedia.org/ontology/team</sem:predicate><sem:object>http://dbpedia.org/resource/Hamburger_SV</sem:object></sem:triple><sem:triple><sem:subject>http://dbpedia.org/resource/Reto_Ziegler</sem:subject><sem:predicate>http://www.w3.org/1999/02/22-rdf-syntax-ns#type</sem:predicate><sem:object>http://dbpedia.org/class/yago/YagoLegalActor</sem:object></sem:triple><sem:triple><sem:subject>http://dbpedia.org/resource/Reto_Ziegler</sem:subject><sem:predicate>http://www.w3.org/1999/02/22-rdf-syntax-ns#type</sem:predicate><sem:object>http://dbpedia.org/class/yago/PhysicalEntity100001930</sem:object></sem:triple><sem:triple><sem:subject>http://dbpedia.org/resource/Reto_Ziegler</sem:subject><sem:predicate>http://www.w3.org/2002/07/owl#sameAs</sem:predicate><sem:object>http://es.dbpedia.org/resource/Reto_Ziegler</sem:object></sem:triple><sem:triple><sem:subject>http://dbpedia.org/resource/Reto_Ziegler</sem:subject><sem:predicate>http://dbpedia.org/property/nationalcaps</sem:predicate><sem:object datatype="http://www.w3.org/2001/XMLSchema#integer">32</sem:object></sem:triple><sem:triple><sem:subject>http://dbpedia.org/resource/Reto_Ziegler</sem:subject><sem:predicate>http://dbpedia.org/ontology/thumbnail</sem:predicate><sem:object>http://commons.wikimedia.org/wiki/Special:FilePath/Reto_Ziegler_2012.jpg?width=300</sem:object></sem:triple><sem:triple><sem:subject>http://dbpedia.org/resource/Reto_Ziegler</sem:subject><sem:predicate>http://xmlns.com/foaf/0.1/name</sem:predicate><sem:object datatype="http://www.w3.org/2001/XMLSchema#string">Reto Ziegler</sem:object></sem:triple><sem:triple><sem:subject>http://dbpedia.org/resource/Reto_Ziegler</sem:subject><sem:predicate>http://dbpedia.org/ontology/careerStation</sem:predicate><sem:object>http://dbpedia.org/resource/Reto_Ziegler__11</sem:object></sem:triple><sem:triple><sem:subject>http://dbpedia.org/resource/Reto_Ziegler</sem:subject><sem:predicate>http://dbpedia.org/ontology/abstract</sem:predicate><sem:object xml:lang="fr">Reto Ziegler, né le 16 janvier 1986 à Genève, est un footballeur suisse, évoluant au poste d'arrière latéral ou milieu gauche.</sem:object></sem:triple><sem:triple><sem:subject>http://dbpedia.org/resource/Reto_Ziegler</sem:subject><sem:predicate>http://www.w3.org/1999/02/22-rdf-syntax-ns#type</sem:predicate><sem:object>http://dbpedia.org/class/yago/Absentee109757653</sem:object></sem:triple><sem:triple><sem:subject>http://dbpedia.org/resource/Reto_Ziegler</sem:subject><sem:predicate>http://dbpedia.org/property/youthclubs</sem:predicate><sem:object>http://dbpedia.org/resource/FC_Gland</sem:object></sem:triple><sem:triple><sem:subject>http://dbpedia.org/resource/Reto_Ziegler</sem:subject><sem:predicate>http://www.w3.org/2002/07/owl#sameAs</sem:predicate><sem:object>http://zh.dbpedia.org/resource/列圖·薛基拿</sem:object></sem:triple><sem:triple><sem:subject>http://dbpedia.org/resource/Reto_Ziegler</sem:subject><sem:predicate>http://dbpedia.org/property/years</sem:predicate><sem:object datatype="http://www.w3.org/2001/XMLSchema#integer">2005</sem:object></sem:triple><sem:triple><sem:subject>http://dbpedia.org/resource/Reto_Ziegler</sem:subject><sem:predicate>http://www.w3.org/2002/07/owl#sameAs</sem:predicate><sem:object>http://yago-knowledge.org/resource/Reto_Ziegler</sem:object></sem:triple><sem:triple><sem:subject>http://dbpedia.org/resource/Reto_Ziegler</sem:subject><sem:predicate>http://www.w3.org/2002/07/owl#sameAs</sem:predicate><sem:object>http://it.dbpedia.org/resource/Reto_Ziegler</sem:object></sem:triple><sem:triple><sem:subject>http://dbpedia.org/resource/Reto_Ziegler</sem:subject><sem:predicate>http://dbpedia.org/property/imageSize</sem:predicate><sem:object datatype="http://www.w3.org/2001/XMLSchema#integer">250</sem:object></sem:triple><sem:triple><sem:subject>http://dbpedia.org/resource/Reto_Ziegler</sem:subject><sem:predicate>http://dbpedia.org/ontology/careerStation</sem:predicate><sem:object>http://dbpedia.org/resource/Reto_Ziegler__12</sem:object></sem:triple><sem:triple><sem:subject>http://dbpedia.org/resource/Reto_Ziegler</sem:subject><sem:predicate>http://dbpedia.org/ontology/team</sem:predicate><sem:object>http://dbpedia.org/resource/Grasshopper_Club_Z%C3%BCrich</sem:object></sem:triple><sem:triple><sem:subject>http://dbpedia.org/resource/Reto_Ziegler</sem:subject><sem:predicate>http://dbpedia.org/ontology/team</sem:predicate><sem:object>http://dbpedia.org/resource/Tottenham_Hotspur_F.C.</sem:object></sem:triple><sem:triple><sem:subject>http://dbpedia.org/resource/Reto_Ziegler</sem:subject><sem:predicate>http://www.w3.org/2000/01/rdf-schema#comment</sem:predicate><sem:object xml:lang="nl">Reto Ziegler (Genève, 16 januari 1986) is een Zwitsers betaald voetballer die bij voorkeur als linksback speelt. Hij staat sinds juli 2011 onder contract bij Juventus. Die club leende hem vervolgens uit aan Fenerbahçe SK, Lokomotiv Moskou, opnieuw Fenerbahçe en US Sassuolo. In maart 2005 debuteerde hij in het Zwitsers voetbalelftal.</sem:object></sem:triple><sem:triple><sem:subject>http://dbpedia.org/resource/Reto_Ziegler</sem:subject><sem:predicate>http://purl.org/dc/terms/subject</sem:predicate><sem:object>http://dbpedia.org/resource/Category:Premier_League_players</sem:object></sem:triple><sem:triple><sem:subject>http://dbpedia.org/resource/Reto_Ziegler</sem:subject><sem:predicate>http://dbpedia.org/property/clubs</sem:predicate><sem:object datatype="http://www.w3.org/2001/XMLSchema#string">→ Lokomotiv Moskva</sem:object></sem:triple><sem:triple><sem:subject>http://dbpedia.org/resource/Reto_Ziegler</sem:subject><sem:predicate>http://purl.org/dc/terms/subject</sem:predicate><sem:object>http://dbpedia.org/resource/Category:S%C3%BCper_Lig_players</sem:object></sem:triple><sem:triple><sem:subject>http://dbpedia.org/resource/Reto_Ziegler</sem:subject><sem:predicate>http://www.w3.org/2002/07/owl#sameAs</sem:predicate><sem:object>http://pt.dbpedia.org/resource/Reto_Ziegler</sem:object></sem:triple><sem:triple><sem:subject>http://dbpedia.org/resource/Reto_Ziegler</sem:subject><sem:predicate>http://dbpedia.org/property/clubs</sem:predicate><sem:object datatype="http://www.w3.org/2001/XMLSchema#string">→ Fenerbahçe</sem:object></sem:triple><sem:triple><sem:subject>http://dbpedia.org/resource/Reto_Ziegler</sem:subject><sem:predicate>http://dbpedia.org/property/youthclubs</sem:predicate><sem:object>http://dbpedia.org/resource/Servette_FC</sem:object></sem:triple><sem:triple><sem:subject>http://dbpedia.org/resource/Reto_Ziegler</sem:subject><sem:predicate>http://www.w3.org/1999/02/22-rdf-syntax-ns#type</sem:predicate><sem:object>http://dbpedia.org/class/yago/Organism100004475</sem:object></sem:triple><sem:triple><sem:subject>http://dbpedia.org/resource/Reto_Ziegler</sem:subject><sem:predicate>http://dbpedia.org/property/youthclubs</sem:predicate><sem:object datatype="http://www.w3.org/2001/XMLSchema#string">US Terre Sainte</sem:object></sem:triple><sem:triple><sem:subject>http://dbpedia.org/resource/Reto_Ziegler</sem:subject><sem:predicate>http://www.w3.org/1999/02/22-rdf-syntax-ns#type</sem:predicate><sem:object>http://schema.org/Person</sem:object></sem:triple><sem:triple><sem:subject>http://dbpedia.org/resource/Reto_Ziegler</sem:subject><sem:predicate>http://www.w3.org/1999/02/22-rdf-syntax-ns#type</sem:predicate><sem:object>http://dbpedia.org/class/yago/PremierLeaguePlayers</sem:object></sem:triple><sem:triple><sem:subject>http://dbpedia.org/resource/Reto_Ziegler</sem:subject><sem:predicate>http://purl.org/dc/terms/subject</sem:predicate><sem:object>http://dbpedia.org/resource/Category:Fenerbah%C3%A7e_footballers</sem:object></sem:triple><sem:triple><sem:subject>http://dbpedia.org/resource/Reto_Ziegler</sem:subject><sem:predicate>http://www.w3.org/2002/07/owl#sameAs</sem:predicate><sem:object>http://fr.dbpedia.org/resource/Reto_Ziegler</sem:object></sem:triple><sem:triple><sem:subject>http://dbpedia.org/resource/Reto_Ziegler</sem:subject><sem:predicate>http://www.w3.org/2002/07/owl#sameAs</sem:predicate><sem:object>http://de.dbpedia.org/resource/Reto_Ziegler</sem:object></sem:triple><sem:triple><sem:subject>http://dbpedia.org/resource/Reto_Ziegler</sem:subject><sem:predicate>http://dbpedia.org/ontology/wikiPageID</sem:predicate><sem:object datatype="http://www.w3.org/2001/XMLSchema#integer">2852092</sem:object></sem:triple><sem:triple><sem:subject>http://dbpedia.org/resource/Reto_Ziegler</sem:subject><sem:predicate>http://dbpedia.org/ontology/team</sem:predicate><sem:object>http://dbpedia.org/resource/U.S._Sassuolo_Calcio</sem:object></sem:triple><sem:triple><sem:subject>http://dbpedia.org/resource/Reto_Ziegler</sem:subject><sem:predicate>http://dbpedia.org/property/youthyears</sem:predicate><sem:object datatype="http://www.w3.org/2001/XMLSchema#integer">1997</sem:object></sem:triple></sem:triples>